msbuddy/__init__.py
msbuddy/base.py
msbuddy/cand.py
msbuddy/export.py
msbuddy/load.py
msbuddy/main.py
msbuddy/main_cmd.py
msbuddy/ml.py
msbuddy/query.py
msbuddy/utils.py
msbuddy-0.3.11.data/scripts/main_cmd.py
msbuddy-0.3.11.dist-info/LICENSE
msbuddy-0.3.11.dist-info/METADATA
msbuddy-0.3.11.dist-info/WHEEL
msbuddy-0.3.11.dist-info/entry_points.txt
msbuddy-0.3.11.dist-info/top_level.txt
msbuddy-0.3.11.dist-info/RECORD
