Metadata-Version: 2.1
Name: msbuddy
Version: 0.3.11
Summary: Molecular formula annotation for MS-based small molecule analysis.
Home-page: https://github.com/Philipbear/msbuddy
Author: Shipei Xing
Author-email: philipxsp@hotmail.com
Project-URL: Bug Tracker, https://github.com/Philipbear/msbuddy/issues
Project-URL: Documentation, https://msbuddy.readthedocs.io/en/latest/
Classifier: Programming Language :: Python :: 3
Classifier: License :: OSI Approved :: Apache Software License
Classifier: Operating System :: OS Independent
Requires-Python: >=3.8
License-File: LICENSE
Requires-Dist: brain-isotopic-distribution
Requires-Dist: numpy
Requires-Dist: numba
Requires-Dist: requests
Requires-Dist: joblib
Requires-Dist: gdown
Requires-Dist: chemparse
Requires-Dist: scipy
Requires-Dist: tqdm
Requires-Dist: pandas
